LICENSE
MANIFEST.in
README.rst
setup.cfg
setup.py
docs/_build/html/.buildinfo
docs/_build/html/genindex.html
docs/_build/html/index.html
docs/_build/html/objects.inv
docs/_build/html/search.html
docs/_build/html/searchindex.js
docs/_build/html/_sources/index.rst.txt
docs/_build/html/_sources/index.txt
docs/_build/html/_static/ajax-loader.gif
docs/_build/html/_static/alabaster.css
docs/_build/html/_static/basic.css
docs/_build/html/_static/comment-bright.png
docs/_build/html/_static/comment-close.png
docs/_build/html/_static/comment.png
docs/_build/html/_static/custom.css
docs/_build/html/_static/doctools.js
docs/_build/html/_static/down-pressed.png
docs/_build/html/_static/down.png
docs/_build/html/_static/file.png
docs/_build/html/_static/jquery-1.11.1.js
docs/_build/html/_static/jquery-3.1.0.js
docs/_build/html/_static/jquery.js
docs/_build/html/_static/minus.png
docs/_build/html/_static/plus.png
docs/_build/html/_static/pygments.css
docs/_build/html/_static/searchtools.js
docs/_build/html/_static/underscore-1.3.1.js
docs/_build/html/_static/underscore.js
docs/_build/html/_static/up-pressed.png
docs/_build/html/_static/up.png
docs/_build/html/_static/websupport.js
rowingphysics/__init__.py
rowingphysics/__main__.py
rowingphysics/crew.py
rowingphysics/erg.py
rowingphysics/expdata.py
rowingphysics/rigging.py
rowingphysics/row_functions.py
rowingphysics/rowingphysics.py
rowingphysics/rowplots.py
rowingphysics/setup.py
rowingphysics/srnumerical.py
rowingphysics.egg-info/PKG-INFO
rowingphysics.egg-info/SOURCES.txt
rowingphysics.egg-info/dependency_links.txt
rowingphysics.egg-info/not-zip-safe
rowingphysics.egg-info/requires.txt
rowingphysics.egg-info/top_level.txt