Metadata-Version: 2.1
Name: rowingphysics
Version: 0.5.1
Summary: Rowing Physics calculations
Home-page: http://sanderroosendaal.wordpress.com
Author: Sander Roosendaal
Author-email: roosendaalsander@gmail.com
License: MIT
Keywords: rowing ergometer concept2
License-File: LICENSE
